{
  "plugin": {
    "manufacturer": "Full Bucket Music",
    "name": "Tricent",
    "version": "1.1.4",
    "format": "VST3",
    "uid": "1858521855"
  },
  "metadata": {
    "version": "1.0",
    "created": "2025-09-25T03:46:18.974Z",
    "author": "plughost-batch",
    "description": "Auto-generated plugin spec for Tricent",
    "parameter_count": 223,
    "tags": [
      "vst3"
    ]
  },
  "parameters": [
    {
      "index": 0,
      "name": "Trident Mode",
      "min": 0,
      "max": 1,
      "default": 1,
      "group": "general",
      "type": "discrete",
      "automatable": true
    },
    {
      "index": 1,
      "name": "Key Assign",
      "min": 0,
      "max": 1,
      "default": 1,
      "group": "general",
      "type": "discrete",
      "automatable": true
    },
    {
      "index": 2,
      "name": "Total Tune",
      "min": 0,
      "max": 1,
      "default": 0.5,
      "group": "general",
      "type": "continuous",
      "automatable": true
    },
    {
      "index": 3,
      "name": "Range Synthe",
      "min": 0,
      "max": 1,
      "default": 0.5,
      "group": "general",
      "type": "discrete",
      "automatable": true
    },
    {
      "index": 4,
      "name": "Range Brass",
      "min": 0,
      "max": 1,
      "default": 0.5,
      "group": "general",
      "type": "discrete",
      "automatable": true
    },
    {
      "index": 5,
      "name": "Range Strings",
      "min": 0,
      "max": 1,
      "default": 0.5,
      "group": "general",
      "type": "discrete",
      "automatable": true
    },
    {
      "index": 6,
      "name": "Split Key",
      "min": 0,
      "max": 1,
      "default": 0.472441,
      "group": "general",
      "type": "discrete",
      "automatable": true
    },
    {
      "index": 7,
      "name": "VCO 1 Octave",
      "min": 0,
      "max": 1,
      "default": 0.5,
      "group": "oscillator",
      "type": "discrete",
      "automatable": true
    },
    {
      "index": 8,
      "name": "VCO 1 Wave",
      "min": 0,
      "max": 1,
      "default": 0,
      "group": "oscillator",
      "type": "discrete",
      "automatable": true
    },
    {
      "index": 9,
      "name": "VCO 1 PW/PWM",
      "min": 0,
      "max": 1,
      "default": 0,
      "group": "oscillator",
      "type": "continuous",
      "automatable": true
    },
    {
      "index": 10,
      "name": "VCO 1 PWM Speed",
      "min": 0,
      "max": 1,
      "default": 0.178781,
      "group": "oscillator",
      "type": "continuous",
      "automatable": true,
      "label": "Hz"
    },
    {
      "index": 11,
      "name": "VCO 2 Octave",
      "min": 0,
      "max": 1,
      "default": 0,
      "group": "oscillator",
      "type": "discrete",
      "automatable": true
    },
    {
      "index": 12,
      "name": "VCO 2 Detune",
      "min": 0,
      "max": 1,
      "default": 0.5,
      "group": "oscillator",
      "type": "continuous",
      "automatable": true
    },
    {
      "index": 13,
      "name": "VCF Cutoff",
      "min": 0,
      "max": 1,
      "default": 1,
      "group": "filter",
      "type": "continuous",
      "automatable": true
    },
    {
      "index": 14,
      "name": "VCF Resonance",
      "min": 0,
      "max": 1,
      "default": 0,
      "group": "filter",
      "type": "continuous",
      "automatable": true
    },
    {
      "index": 15,
      "name": "VCF KBF Track",
      "min": 0,
      "max": 1,
      "default": 0,
      "group": "general",
      "type": "discrete",
      "automatable": true
    },
    {
      "index": 16,
      "name": "VCF EG Intensity",
      "min": 0,
      "max": 1,
      "default": 0.5,
      "group": "general",
      "type": "continuous",
      "automatable": true
    },
    {
      "index": 17,
      "name": "VCF Attack",
      "min": 0,
      "max": 1,
      "default": 0,
      "group": "envelope",
      "type": "continuous",
      "automatable": true
    },
    {
      "index": 18,
      "name": "VCF Decay",
      "min": 0,
      "max": 1,
      "default": 0,
      "group": "envelope",
      "type": "continuous",
      "automatable": true
    },
    {
      "index": 19,
      "name": "VCF Sustain",
      "min": 0,
      "max": 1,
      "default": 0,
      "group": "envelope",
      "type": "continuous",
      "automatable": true
    },
    {
      "index": 20,
      "name": "VCF Release",
      "min": 0,
      "max": 1,
      "default": 0,
      "group": "envelope",
      "type": "continuous",
      "automatable": true
    },
    {
      "index": 21,
      "name": "VCA Attack",
      "min": 0,
      "max": 1,
      "default": 0,
      "group": "envelope",
      "type": "continuous",
      "automatable": true
    },
    {
      "index": 22,
      "name": "VCA Decay",
      "min": 0,
      "max": 1,
      "default": 0,
      "group": "envelope",
      "type": "continuous",
      "automatable": true
    },
    {
      "index": 23,
      "name": "VCA Sustain",
      "min": 0,
      "max": 1,
      "default": 1,
      "group": "envelope",
      "type": "continuous",
      "automatable": true
    },
    {
      "index": 24,
      "name": "VCA Release",
      "min": 0,
      "max": 1,
      "default": 0,
      "group": "envelope",
      "type": "continuous",
      "automatable": true
    },
    {
      "index": 25,
      "name": "VCA Attenuator",
      "min": 0,
      "max": 1,
      "default": 0.5,
      "group": "general",
      "type": "continuous",
      "automatable": true
    },
    {
      "index": 26,
      "name": "VCA Auto Damp",
      "min": 0,
      "max": 1,
      "default": 0,
      "group": "general",
      "type": "discrete",
      "automatable": true
    },
    {
      "index": 27,
      "name": "Brass Cutoff",
      "min": 0,
      "max": 1,
      "default": 1,
      "group": "filter",
      "type": "continuous",
      "automatable": true
    },
    {
      "index": 28,
      "name": "Brass Resonance",
      "min": 0,
      "max": 1,
      "default": 0,
      "group": "filter",
      "type": "continuous",
      "automatable": true
    },
    {
      "index": 29,
      "name": "Brass Silent Notes",
      "min": 0,
      "max": 1,
      "default": 0,
      "group": "general",
      "type": "discrete",
      "automatable": true
    },
    {
      "index": 30,
      "name": "Brass EG Intensity",
      "min": 0,
      "max": 1,
      "default": 0,
      "group": "general",
      "type": "continuous",
      "automatable": true
    },
    {
      "index": 31,
      "name": "Brass Attack",
      "min": 0,
      "max": 1,
      "default": 0,
      "group": "envelope",
      "type": "continuous",
      "automatable": true
    },
    {
      "index": 32,
      "name": "Brass Decay",
      "min": 0,
      "max": 1,
      "default": 0,
      "group": "envelope",
      "type": "continuous",
      "automatable": true
    },
    {
      "index": 33,
      "name": "Brass Sustain",
      "min": 0,
      "max": 1,
      "default": 1,
      "group": "envelope",
      "type": "continuous",
      "automatable": true
    },
    {
      "index": 34,
      "name": "Brass Release",
      "min": 0,
      "max": 1,
      "default": 0,
      "group": "envelope",
      "type": "continuous",
      "automatable": true
    },
    {
      "index": 35,
      "name": "Brass 16'",
      "min": 0,
      "max": 1,
      "default": 1,
      "group": "general",
      "type": "discrete",
      "automatable": true
    },
    {
      "index": 36,
      "name": "Brass 8'",
      "min": 0,
      "max": 1,
      "default": 0,
      "group": "general",
      "type": "discrete",
      "automatable": true
    },
    {
      "index": 37,
      "name": "Brass Multi Trigger",
      "min": 0,
      "max": 1,
      "default": 0,
      "group": "general",
      "type": "discrete",
      "automatable": true
    },
    {
      "index": 38,
      "name": "Brass Trigger Select",
      "min": 0,
      "max": 1,
      "default": 0,
      "group": "general",
      "type": "discrete",
      "automatable": true
    },
    {
      "index": 39,
      "name": "Strings Attack",
      "min": 0,
      "max": 1,
      "default": 0.3,
      "group": "envelope",
      "type": "continuous",
      "automatable": true
    },
    {
      "index": 40,
      "name": "Strings Release",
      "min": 0,
      "max": 1,
      "default": 0.4,
      "group": "envelope",
      "type": "continuous",
      "automatable": true
    },
    {
      "index": 41,
      "name": "Strings EQ High",
      "min": 0,
      "max": 1,
      "default": 0.5,
      "group": "general",
      "type": "continuous",
      "automatable": true
    },
    {
      "index": 42,
      "name": "Strings EQ Low",
      "min": 0,
      "max": 1,
      "default": 0.5,
      "group": "general",
      "type": "continuous",
      "automatable": true
    },
    {
      "index": 43,
      "name": "Strings Bowing Level",
      "min": 0,
      "max": 1,
      "default": 0.5,
      "group": "mixer",
      "type": "continuous",
      "automatable": true
    },
    {
      "index": 44,
      "name": "Strings Bowing Tone",
      "min": 0,
      "max": 1,
      "default": 0.5,
      "group": "general",
      "type": "continuous",
      "automatable": true
    },
    {
      "index": 45,
      "name": "Strings Vibrato Delay",
      "min": 0,
      "max": 1,
      "default": 0.5,
      "group": "effects",
      "type": "continuous",
      "automatable": true
    },
    {
      "index": 46,
      "name": "Strings Vibrato Speed",
      "min": 0,
      "max": 1,
      "default": 0.469018,
      "group": "general",
      "type": "continuous",
      "automatable": true,
      "label": "Hz"
    },
    {
      "index": 47,
      "name": "Strings Vibrato Intensity",
      "min": 0,
      "max": 1,
      "default": 0,
      "group": "general",
      "type": "continuous",
      "automatable": true
    },
    {
      "index": 48,
      "name": "Strings KBD Balance",
      "min": 0,
      "max": 1,
      "default": 0,
      "group": "general",
      "type": "continuous",
      "automatable": true
    },
    {
      "index": 49,
      "name": "Strings 16'",
      "min": 0,
      "max": 1,
      "default": 0,
      "group": "general",
      "type": "discrete",
      "automatable": true
    },
    {
      "index": 50,
      "name": "Strings 8'",
      "min": 0,
      "max": 1,
      "default": 1,
      "group": "general",
      "type": "discrete",
      "automatable": true
    },
    {
      "index": 51,
      "name": "Strings 4'",
      "min": 0,
      "max": 1,
      "default": 0,
      "group": "general",
      "type": "discrete",
      "automatable": true
    },
    {
      "index": 52,
      "name": "Strings Bowing",
      "min": 0,
      "max": 1,
      "default": 0,
      "group": "general",
      "type": "discrete",
      "automatable": true
    },
    {
      "index": 53,
      "name": "Strings Vibrato",
      "min": 0,
      "max": 1,
      "default": 0,
      "group": "general",
      "type": "discrete",
      "automatable": true
    },
    {
      "index": 54,
      "name": "Strings Ensemble",
      "min": 0,
      "max": 1,
      "default": 0,
      "group": "general",
      "type": "discrete",
      "automatable": true
    },
    {
      "index": 55,
      "name": "Vib. Intensity",
      "min": 0,
      "max": 1,
      "default": 0.316228,
      "group": "general",
      "type": "continuous",
      "automatable": true
    },
    {
      "index": 56,
      "name": "Vib. Delay",
      "min": 0,
      "max": 1,
      "default": 0,
      "group": "effects",
      "type": "continuous",
      "automatable": true
    },
    {
      "index": 57,
      "name": "Wheel Vib. Intensity",
      "min": 0,
      "max": 1,
      "default": 0.316228,
      "group": "general",
      "type": "continuous",
      "automatable": true
    },
    {
      "index": 58,
      "name": "Wheel Vib. Speed",
      "min": 0,
      "max": 1,
      "default": 0.469018,
      "group": "general",
      "type": "continuous",
      "automatable": true,
      "label": "Hz"
    },
    {
      "index": 59,
      "name": "Wheel Mode",
      "min": 0,
      "max": 1,
      "default": 1,
      "group": "general",
      "type": "discrete",
      "automatable": true
    },
    {
      "index": 60,
      "name": "Pitch Bend",
      "min": 0,
      "max": 1,
      "default": 0.583333,
      "group": "general",
      "type": "continuous",
      "automatable": true
    },
    {
      "index": 61,
      "name": "Flanger Speed",
      "min": 0,
      "max": 1,
      "default": 0.167219,
      "group": "general",
      "type": "continuous",
      "automatable": true,
      "label": "Hz"
    },
    {
      "index": 62,
      "name": "Flanger Feedback",
      "min": 0,
      "max": 1,
      "default": 0.3,
      "group": "general",
      "type": "continuous",
      "automatable": true
    },
    {
      "index": 63,
      "name": "Flanger Intensity",
      "min": 0,
      "max": 1,
      "default": 0.5,
      "group": "general",
      "type": "continuous",
      "automatable": true
    },
    {
      "index": 64,
      "name": "Flanger Manual",
      "min": 0,
      "max": 1,
      "default": 0.5,
      "group": "general",
      "type": "continuous",
      "automatable": true
    },
    {
      "index": 65,
      "name": "Flanger Synthe",
      "min": 0,
      "max": 1,
      "default": 0,
      "group": "general",
      "type": "discrete",
      "automatable": true
    },
    {
      "index": 66,
      "name": "Flanger Brass",
      "min": 0,
      "max": 1,
      "default": 0,
      "group": "general",
      "type": "discrete",
      "automatable": true
    },
    {
      "index": 67,
      "name": "Flanger Strings",
      "min": 0,
      "max": 1,
      "default": 0,
      "group": "general",
      "type": "discrete",
      "automatable": true
    },
    {
      "index": 68,
      "name": "Total Volume",
      "min": 0,
      "max": 1,
      "default": 0.5,
      "group": "mixer",
      "type": "continuous",
      "automatable": true
    },
    {
      "index": 69,
      "name": "Volume Synthe",
      "min": 0,
      "max": 1,
      "default": 0.5,
      "group": "mixer",
      "type": "continuous",
      "automatable": true
    },
    {
      "index": 70,
      "name": "Volume Brass",
      "min": 0,
      "max": 1,
      "default": 0.5,
      "group": "mixer",
      "type": "continuous",
      "automatable": true
    },
    {
      "index": 71,
      "name": "Volume Strings",
      "min": 0,
      "max": 1,
      "default": 0.5,
      "group": "mixer",
      "type": "continuous",
      "automatable": true
    },
    {
      "index": 72,
      "name": "Output Synthe",
      "min": 0,
      "max": 1,
      "default": 1,
      "group": "general",
      "type": "discrete",
      "automatable": true
    },
    {
      "index": 73,
      "name": "Output Brass",
      "min": 0,
      "max": 1,
      "default": 0,
      "group": "general",
      "type": "discrete",
      "automatable": true
    },
    {
      "index": 74,
      "name": "Output Strings",
      "min": 0,
      "max": 1,
      "default": 0,
      "group": "general",
      "type": "discrete",
      "automatable": true
    },
    {
      "index": 75,
      "name": "Pan Synthe",
      "min": 0,
      "max": 1,
      "default": 0.5,
      "group": "panning",
      "type": "continuous",
      "automatable": true
    },
    {
      "index": 76,
      "name": "Pan Brass",
      "min": 0,
      "max": 1,
      "default": 0.5,
      "group": "panning",
      "type": "continuous",
      "automatable": true
    },
    {
      "index": 77,
      "name": "Pan Strings",
      "min": 0,
      "max": 1,
      "default": 0.5,
      "group": "panning",
      "type": "continuous",
      "automatable": true
    },
    {
      "index": 78,
      "name": "Velocity Synthe",
      "min": 0,
      "max": 1,
      "default": 0,
      "group": "general",
      "type": "continuous",
      "automatable": true
    },
    {
      "index": 79,
      "name": "Velocity Brass",
      "min": 0,
      "max": 1,
      "default": 0,
      "group": "general",
      "type": "continuous",
      "automatable": true
    },
    {
      "index": 80,
      "name": "Velocity Strings",
      "min": 0,
      "max": 1,
      "default": 0,
      "group": "general",
      "type": "continuous",
      "automatable": true
    },
    {
      "index": 81,
      "name": "Velocity Synthe VCF",
      "min": 0,
      "max": 1,
      "default": 0,
      "group": "general",
      "type": "continuous",
      "automatable": true
    },
    {
      "index": 82,
      "name": "Velocity Brass VCF",
      "min": 0,
      "max": 1,
      "default": 0,
      "group": "general",
      "type": "continuous",
      "automatable": true
    },
    {
      "index": 83,
      "name": "Stereo Flanger",
      "min": 0,
      "max": 1,
      "default": 0,
      "group": "general",
      "type": "discrete",
      "automatable": true
    },
    {
      "index": 84,
      "name": "Stereo Ensemble",
      "min": 0,
      "max": 1,
      "default": 0,
      "group": "general",
      "type": "discrete",
      "automatable": true
    },
    {
      "index": 85,
      "name": "Detune Brass",
      "min": 0,
      "max": 1,
      "default": 0.5,
      "group": "general",
      "type": "continuous",
      "automatable": true
    },
    {
      "index": 86,
      "name": "Detune Strings",
      "min": 0,
      "max": 1,
      "default": 0.5,
      "group": "general",
      "type": "continuous",
      "automatable": true
    },
    {
      "index": 87,
      "name": "Vib. Delay Time",
      "min": 0,
      "max": 1,
      "default": 0.5,
      "group": "effects",
      "type": "continuous",
      "automatable": true
    },
    {
      "index": 88,
      "name": "Ens. LFO1 Speed",
      "min": 0,
      "max": 1,
      "default": 0.50038,
      "group": "lfo",
      "type": "continuous",
      "automatable": true,
      "label": "Hz"
    },
    {
      "index": 89,
      "name": "Ens. LFO2 Speed",
      "min": 0,
      "max": 1,
      "default": 0.105645,
      "group": "lfo",
      "type": "continuous",
      "automatable": true,
      "label": "Hz"
    },
    {
      "index": 90,
      "name": "Ens.1 Amount",
      "min": 0,
      "max": 1,
      "default": 0.3,
      "group": "general",
      "type": "continuous",
      "automatable": true
    },
    {
      "index": 91,
      "name": "Ens.2 Amount",
      "min": 0,
      "max": 1,
      "default": 0.3,
      "group": "general",
      "type": "continuous",
      "automatable": true
    },
    {
      "index": 92,
      "name": "Ens.3 Amount",
      "min": 0,
      "max": 1,
      "default": 0.3,
      "group": "general",
      "type": "continuous",
      "automatable": true
    },
    {
      "index": 93,
      "name": "BankSel.MSB",
      "min": 0,
      "max": 1,
      "default": 0,
      "group": "general",
      "type": "continuous",
      "automatable": false
    },
    {
      "index": 94,
      "name": "Modulation",
      "min": 0,
      "max": 1,
      "default": 0,
      "group": "general",
      "type": "continuous",
      "automatable": false
    },
    {
      "index": 95,
      "name": "BreathCtrl",
      "min": 0,
      "max": 1,
      "default": 0,
      "group": "general",
      "type": "continuous",
      "automatable": false
    },
    {
      "index": 96,
      "name": "Contr. 3",
      "min": 0,
      "max": 1,
      "default": 0,
      "group": "general",
      "type": "continuous",
      "automatable": false
    },
    {
      "index": 97,
      "name": "Foot Ctrl",
      "min": 0,
      "max": 1,
      "default": 0,
      "group": "general",
      "type": "continuous",
      "automatable": false
    },
    {
      "index": 98,
      "name": "Porta.Time",
      "min": 0,
      "max": 1,
      "default": 0,
      "group": "general",
      "type": "continuous",
      "automatable": false
    },
    {
      "index": 99,
      "name": "DataEntMSB",
      "min": 0,
      "max": 1,
      "default": 0,
      "group": "general",
      "type": "continuous",
      "automatable": false
    },
    {
      "index": 100,
      "name": "MainVolume",
      "min": 0,
      "max": 1,
      "default": 0,
      "group": "mixer",
      "type": "continuous",
      "automatable": false
    },
    {
      "index": 101,
      "name": "Balance",
      "min": 0,
      "max": 1,
      "default": 0,
      "group": "general",
      "type": "continuous",
      "automatable": false
    },
    {
      "index": 102,
      "name": "Contr. 9",
      "min": 0,
      "max": 1,
      "default": 0,
      "group": "general",
      "type": "continuous",
      "automatable": false
    },
    {
      "index": 103,
      "name": "Pan",
      "min": 0,
      "max": 1,
      "default": 0,
      "group": "panning",
      "type": "continuous",
      "automatable": false
    },
    {
      "index": 104,
      "name": "Expression",
      "min": 0,
      "max": 1,
      "default": 0,
      "group": "general",
      "type": "continuous",
      "automatable": false
    },
    {
      "index": 105,
      "name": "FXControl1",
      "min": 0,
      "max": 1,
      "default": 0,
      "group": "general",
      "type": "continuous",
      "automatable": false
    },
    {
      "index": 106,
      "name": "FXControl2",
      "min": 0,
      "max": 1,
      "default": 0,
      "group": "general",
      "type": "continuous",
      "automatable": false
    },
    {
      "index": 107,
      "name": "Contr. 14",
      "min": 0,
      "max": 1,
      "default": 0,
      "group": "general",
      "type": "continuous",
      "automatable": false
    },
    {
      "index": 108,
      "name": "Contr. 15",
      "min": 0,
      "max": 1,
      "default": 0,
      "group": "general",
      "type": "continuous",
      "automatable": false
    },
    {
      "index": 109,
      "name": "Gen.Purp.1",
      "min": 0,
      "max": 1,
      "default": 0,
      "group": "general",
      "type": "continuous",
      "automatable": false
    },
    {
      "index": 110,
      "name": "Gen.Purp.2",
      "min": 0,
      "max": 1,
      "default": 0,
      "group": "general",
      "type": "continuous",
      "automatable": false
    },
    {
      "index": 111,
      "name": "Gen.Purp.3",
      "min": 0,
      "max": 1,
      "default": 0,
      "group": "general",
      "type": "continuous",
      "automatable": false
    },
    {
      "index": 112,
      "name": "Gen.Purp.4",
      "min": 0,
      "max": 1,
      "default": 0,
      "group": "general",
      "type": "continuous",
      "automatable": false
    },
    {
      "index": 113,
      "name": "Contr. 20",
      "min": 0,
      "max": 1,
      "default": 0,
      "group": "general",
      "type": "continuous",
      "automatable": false
    },
    {
      "index": 114,
      "name": "Contr. 21",
      "min": 0,
      "max": 1,
      "default": 0,
      "group": "general",
      "type": "continuous",
      "automatable": false
    },
    {
      "index": 115,
      "name": "Contr. 22",
      "min": 0,
      "max": 1,
      "default": 0,
      "group": "general",
      "type": "continuous",
      "automatable": false
    },
    {
      "index": 116,
      "name": "Contr. 23",
      "min": 0,
      "max": 1,
      "default": 0,
      "group": "general",
      "type": "continuous",
      "automatable": false
    },
    {
      "index": 117,
      "name": "Contr. 24",
      "min": 0,
      "max": 1,
      "default": 0,
      "group": "general",
      "type": "continuous",
      "automatable": false
    },
    {
      "index": 118,
      "name": "Contr. 25",
      "min": 0,
      "max": 1,
      "default": 0,
      "group": "general",
      "type": "continuous",
      "automatable": false
    },
    {
      "index": 119,
      "name": "Contr. 26",
      "min": 0,
      "max": 1,
      "default": 0,
      "group": "general",
      "type": "continuous",
      "automatable": false
    },
    {
      "index": 120,
      "name": "Contr. 27",
      "min": 0,
      "max": 1,
      "default": 0,
      "group": "general",
      "type": "continuous",
      "automatable": false
    },
    {
      "index": 121,
      "name": "Contr. 28",
      "min": 0,
      "max": 1,
      "default": 0,
      "group": "general",
      "type": "continuous",
      "automatable": false
    },
    {
      "index": 122,
      "name": "Contr. 29",
      "min": 0,
      "max": 1,
      "default": 0,
      "group": "general",
      "type": "continuous",
      "automatable": false
    },
    {
      "index": 123,
      "name": "Contr. 30",
      "min": 0,
      "max": 1,
      "default": 0,
      "group": "general",
      "type": "continuous",
      "automatable": false
    },
    {
      "index": 124,
      "name": "Contr. 31",
      "min": 0,
      "max": 1,
      "default": 0,
      "group": "general",
      "type": "continuous",
      "automatable": false
    },
    {
      "index": 125,
      "name": "BankSel.LSB",
      "min": 0,
      "max": 1,
      "default": 0,
      "group": "general",
      "type": "continuous",
      "automatable": false
    },
    {
      "index": 126,
      "name": "Modul. LSB",
      "min": 0,
      "max": 1,
      "default": 0,
      "group": "general",
      "type": "continuous",
      "automatable": false
    },
    {
      "index": 127,
      "name": "BrthCt LSB",
      "min": 0,
      "max": 1,
      "default": 0,
      "group": "general",
      "type": "continuous",
      "automatable": false
    },
    {
      "index": 128,
      "name": "Contr. 35",
      "min": 0,
      "max": 1,
      "default": 0,
      "group": "general",
      "type": "continuous",
      "automatable": false
    },
    {
      "index": 129,
      "name": "FootCt LSB",
      "min": 0,
      "max": 1,
      "default": 0,
      "group": "general",
      "type": "continuous",
      "automatable": false
    },
    {
      "index": 130,
      "name": "Port.T LSB",
      "min": 0,
      "max": 1,
      "default": 0,
      "group": "general",
      "type": "continuous",
      "automatable": false
    },
    {
      "index": 131,
      "name": "DataEntLSB",
      "min": 0,
      "max": 1,
      "default": 0,
      "group": "general",
      "type": "continuous",
      "automatable": false
    },
    {
      "index": 132,
      "name": "MainVolLSB",
      "min": 0,
      "max": 1,
      "default": 0,
      "group": "general",
      "type": "continuous",
      "automatable": false
    },
    {
      "index": 133,
      "name": "BalanceLSB",
      "min": 0,
      "max": 1,
      "default": 0,
      "group": "general",
      "type": "continuous",
      "automatable": false
    },
    {
      "index": 134,
      "name": "Contr. 41",
      "min": 0,
      "max": 1,
      "default": 0,
      "group": "general",
      "type": "continuous",
      "automatable": false
    },
    {
      "index": 135,
      "name": "Pan LSB",
      "min": 0,
      "max": 1,
      "default": 0,
      "group": "panning",
      "type": "continuous",
      "automatable": false
    },
    {
      "index": 136,
      "name": "Expr. LSB",
      "min": 0,
      "max": 1,
      "default": 0,
      "group": "general",
      "type": "continuous",
      "automatable": false
    },
    {
      "index": 137,
      "name": "Contr. 44",
      "min": 0,
      "max": 1,
      "default": 0,
      "group": "general",
      "type": "continuous",
      "automatable": false
    },
    {
      "index": 138,
      "name": "Contr. 45",
      "min": 0,
      "max": 1,
      "default": 0,
      "group": "general",
      "type": "continuous",
      "automatable": false
    },
    {
      "index": 139,
      "name": "Contr. 46",
      "min": 0,
      "max": 1,
      "default": 0,
      "group": "general",
      "type": "continuous",
      "automatable": false
    },
    {
      "index": 140,
      "name": "Contr. 47",
      "min": 0,
      "max": 1,
      "default": 0,
      "group": "general",
      "type": "continuous",
      "automatable": false
    },
    {
      "index": 141,
      "name": "Gen.P.1LSB",
      "min": 0,
      "max": 1,
      "default": 0,
      "group": "general",
      "type": "continuous",
      "automatable": false
    },
    {
      "index": 142,
      "name": "Gen.P.2LSB",
      "min": 0,
      "max": 1,
      "default": 0,
      "group": "general",
      "type": "continuous",
      "automatable": false
    },
    {
      "index": 143,
      "name": "Gen.P.3LSB",
      "min": 0,
      "max": 1,
      "default": 0,
      "group": "general",
      "type": "continuous",
      "automatable": false
    },
    {
      "index": 144,
      "name": "Gen.P.4LSB",
      "min": 0,
      "max": 1,
      "default": 0,
      "group": "general",
      "type": "continuous",
      "automatable": false
    },
    {
      "index": 145,
      "name": "Contr. 52",
      "min": 0,
      "max": 1,
      "default": 0,
      "group": "general",
      "type": "continuous",
      "automatable": false
    },
    {
      "index": 146,
      "name": "Contr. 53",
      "min": 0,
      "max": 1,
      "default": 0,
      "group": "general",
      "type": "continuous",
      "automatable": false
    },
    {
      "index": 147,
      "name": "Contr. 54",
      "min": 0,
      "max": 1,
      "default": 0,
      "group": "general",
      "type": "continuous",
      "automatable": false
    },
    {
      "index": 148,
      "name": "Contr. 55",
      "min": 0,
      "max": 1,
      "default": 0,
      "group": "general",
      "type": "continuous",
      "automatable": false
    },
    {
      "index": 149,
      "name": "Contr. 56",
      "min": 0,
      "max": 1,
      "default": 0,
      "group": "general",
      "type": "continuous",
      "automatable": false
    },
    {
      "index": 150,
      "name": "Contr. 57",
      "min": 0,
      "max": 1,
      "default": 0,
      "group": "general",
      "type": "continuous",
      "automatable": false
    },
    {
      "index": 151,
      "name": "Contr. 58",
      "min": 0,
      "max": 1,
      "default": 0,
      "group": "general",
      "type": "continuous",
      "automatable": false
    },
    {
      "index": 152,
      "name": "Contr. 59",
      "min": 0,
      "max": 1,
      "default": 0,
      "group": "general",
      "type": "continuous",
      "automatable": false
    },
    {
      "index": 153,
      "name": "Contr. 60",
      "min": 0,
      "max": 1,
      "default": 0,
      "group": "general",
      "type": "continuous",
      "automatable": false
    },
    {
      "index": 154,
      "name": "Contr. 61",
      "min": 0,
      "max": 1,
      "default": 0,
      "group": "general",
      "type": "continuous",
      "automatable": false
    },
    {
      "index": 155,
      "name": "Contr. 62",
      "min": 0,
      "max": 1,
      "default": 0,
      "group": "general",
      "type": "continuous",
      "automatable": false
    },
    {
      "index": 156,
      "name": "Contr. 63",
      "min": 0,
      "max": 1,
      "default": 0,
      "group": "general",
      "type": "continuous",
      "automatable": false
    },
    {
      "index": 157,
      "name": "Damper Ped",
      "min": 0,
      "max": 1,
      "default": 0,
      "group": "general",
      "type": "continuous",
      "automatable": false
    },
    {
      "index": 158,
      "name": "Porta. Ped",
      "min": 0,
      "max": 1,
      "default": 0,
      "group": "general",
      "type": "continuous",
      "automatable": false
    },
    {
      "index": 159,
      "name": "Sostenuto ",
      "min": 0,
      "max": 1,
      "default": 0,
      "group": "general",
      "type": "continuous",
      "automatable": false
    },
    {
      "index": 160,
      "name": "Soft Pedal",
      "min": 0,
      "max": 1,
      "default": 0,
      "group": "general",
      "type": "continuous",
      "automatable": false
    },
    {
      "index": 161,
      "name": "Legato Sw",
      "min": 0,
      "max": 1,
      "default": 0,
      "group": "general",
      "type": "continuous",
      "automatable": false
    },
    {
      "index": 162,
      "name": "Hold 2",
      "min": 0,
      "max": 1,
      "default": 0,
      "group": "general",
      "type": "continuous",
      "automatable": false
    },
    {
      "index": 163,
      "name": "SoundCont 1",
      "min": 0,
      "max": 1,
      "default": 0,
      "group": "general",
      "type": "continuous",
      "automatable": false
    },
    {
      "index": 164,
      "name": "SoundCont 2",
      "min": 0,
      "max": 1,
      "default": 0,
      "group": "general",
      "type": "continuous",
      "automatable": false
    },
    {
      "index": 165,
      "name": "SoundCont 3",
      "min": 0,
      "max": 1,
      "default": 0,
      "group": "general",
      "type": "continuous",
      "automatable": false
    },
    {
      "index": 166,
      "name": "SoundCont 4",
      "min": 0,
      "max": 1,
      "default": 0,
      "group": "general",
      "type": "continuous",
      "automatable": false
    },
    {
      "index": 167,
      "name": "SoundCont 5",
      "min": 0,
      "max": 1,
      "default": 0,
      "group": "general",
      "type": "continuous",
      "automatable": false
    },
    {
      "index": 168,
      "name": "SoundCont 6",
      "min": 0,
      "max": 1,
      "default": 0,
      "group": "general",
      "type": "continuous",
      "automatable": false
    },
    {
      "index": 169,
      "name": "SoundCont 7",
      "min": 0,
      "max": 1,
      "default": 0,
      "group": "general",
      "type": "continuous",
      "automatable": false
    },
    {
      "index": 170,
      "name": "SoundCont 8",
      "min": 0,
      "max": 1,
      "default": 0,
      "group": "general",
      "type": "continuous",
      "automatable": false
    },
    {
      "index": 171,
      "name": "SoundCont 9",
      "min": 0,
      "max": 1,
      "default": 0,
      "group": "general",
      "type": "continuous",
      "automatable": false
    },
    {
      "index": 172,
      "name": "SoundCont 10",
      "min": 0,
      "max": 1,
      "default": 0,
      "group": "general",
      "type": "continuous",
      "automatable": false
    },
    {
      "index": 173,
      "name": "Gen.Purp.5",
      "min": 0,
      "max": 1,
      "default": 0,
      "group": "general",
      "type": "continuous",
      "automatable": false
    },
    {
      "index": 174,
      "name": "Gen.Purp.6",
      "min": 0,
      "max": 1,
      "default": 0,
      "group": "general",
      "type": "continuous",
      "automatable": false
    },
    {
      "index": 175,
      "name": "Gen.Purp.7",
      "min": 0,
      "max": 1,
      "default": 0,
      "group": "general",
      "type": "continuous",
      "automatable": false
    },
    {
      "index": 176,
      "name": "Gen.Purp.8",
      "min": 0,
      "max": 1,
      "default": 0,
      "group": "general",
      "type": "continuous",
      "automatable": false
    },
    {
      "index": 177,
      "name": "Portamento",
      "min": 0,
      "max": 1,
      "default": 0,
      "group": "general",
      "type": "continuous",
      "automatable": false
    },
    {
      "index": 178,
      "name": "Contr. 85",
      "min": 0,
      "max": 1,
      "default": 0,
      "group": "general",
      "type": "continuous",
      "automatable": false
    },
    {
      "index": 179,
      "name": "Contr. 86",
      "min": 0,
      "max": 1,
      "default": 0,
      "group": "general",
      "type": "continuous",
      "automatable": false
    },
    {
      "index": 180,
      "name": "Contr. 87",
      "min": 0,
      "max": 1,
      "default": 0,
      "group": "general",
      "type": "continuous",
      "automatable": false
    },
    {
      "index": 181,
      "name": "Contr. 88",
      "min": 0,
      "max": 1,
      "default": 0,
      "group": "general",
      "type": "continuous",
      "automatable": false
    },
    {
      "index": 182,
      "name": "Contr. 89",
      "min": 0,
      "max": 1,
      "default": 0,
      "group": "general",
      "type": "continuous",
      "automatable": false
    },
    {
      "index": 183,
      "name": "Contr. 90",
      "min": 0,
      "max": 1,
      "default": 0,
      "group": "general",
      "type": "continuous",
      "automatable": false
    },
    {
      "index": 184,
      "name": "FX 1 Depth",
      "min": 0,
      "max": 1,
      "default": 0,
      "group": "general",
      "type": "continuous",
      "automatable": false
    },
    {
      "index": 185,
      "name": "FX 2 Depth",
      "min": 0,
      "max": 1,
      "default": 0,
      "group": "general",
      "type": "continuous",
      "automatable": false
    },
    {
      "index": 186,
      "name": "FX 3 Depth",
      "min": 0,
      "max": 1,
      "default": 0,
      "group": "general",
      "type": "continuous",
      "automatable": false
    },
    {
      "index": 187,
      "name": "FX 4 Depth",
      "min": 0,
      "max": 1,
      "default": 0,
      "group": "general",
      "type": "continuous",
      "automatable": false
    },
    {
      "index": 188,
      "name": "FX 5 Depth",
      "min": 0,
      "max": 1,
      "default": 0,
      "group": "general",
      "type": "continuous",
      "automatable": false
    },
    {
      "index": 189,
      "name": "Data Incr",
      "min": 0,
      "max": 1,
      "default": 0,
      "group": "general",
      "type": "continuous",
      "automatable": false
    },
    {
      "index": 190,
      "name": "Data Decr",
      "min": 0,
      "max": 1,
      "default": 0,
      "group": "general",
      "type": "continuous",
      "automatable": false
    },
    {
      "index": 191,
      "name": "Non-RegLSB",
      "min": 0,
      "max": 1,
      "default": 0,
      "group": "general",
      "type": "continuous",
      "automatable": false
    },
    {
      "index": 192,
      "name": "Non-RegMSB",
      "min": 0,
      "max": 1,
      "default": 0,
      "group": "general",
      "type": "continuous",
      "automatable": false
    },
    {
      "index": 193,
      "name": "Reg LSB",
      "min": 0,
      "max": 1,
      "default": 0,
      "group": "general",
      "type": "continuous",
      "automatable": false
    },
    {
      "index": 194,
      "name": "Reg MSB",
      "min": 0,
      "max": 1,
      "default": 0,
      "group": "general",
      "type": "continuous",
      "automatable": false
    },
    {
      "index": 195,
      "name": "Contr. 102",
      "min": 0,
      "max": 1,
      "default": 0,
      "group": "general",
      "type": "continuous",
      "automatable": false
    },
    {
      "index": 196,
      "name": "Contr. 103",
      "min": 0,
      "max": 1,
      "default": 0,
      "group": "general",
      "type": "continuous",
      "automatable": false
    },
    {
      "index": 197,
      "name": "Contr. 104",
      "min": 0,
      "max": 1,
      "default": 0,
      "group": "general",
      "type": "continuous",
      "automatable": false
    },
    {
      "index": 198,
      "name": "Contr. 105",
      "min": 0,
      "max": 1,
      "default": 0,
      "group": "general",
      "type": "continuous",
      "automatable": false
    },
    {
      "index": 199,
      "name": "Contr. 106",
      "min": 0,
      "max": 1,
      "default": 0,
      "group": "general",
      "type": "continuous",
      "automatable": false
    },
    {
      "index": 200,
      "name": "Contr. 107",
      "min": 0,
      "max": 1,
      "default": 0,
      "group": "general",
      "type": "continuous",
      "automatable": false
    },
    {
      "index": 201,
      "name": "Contr. 108",
      "min": 0,
      "max": 1,
      "default": 0,
      "group": "general",
      "type": "continuous",
      "automatable": false
    },
    {
      "index": 202,
      "name": "Contr. 109",
      "min": 0,
      "max": 1,
      "default": 0,
      "group": "general",
      "type": "continuous",
      "automatable": false
    },
    {
      "index": 203,
      "name": "Contr. 110",
      "min": 0,
      "max": 1,
      "default": 0,
      "group": "general",
      "type": "continuous",
      "automatable": false
    },
    {
      "index": 204,
      "name": "Contr. 111",
      "min": 0,
      "max": 1,
      "default": 0,
      "group": "general",
      "type": "continuous",
      "automatable": false
    },
    {
      "index": 205,
      "name": "Contr. 112",
      "min": 0,
      "max": 1,
      "default": 0,
      "group": "general",
      "type": "continuous",
      "automatable": false
    },
    {
      "index": 206,
      "name": "Contr. 113",
      "min": 0,
      "max": 1,
      "default": 0,
      "group": "general",
      "type": "continuous",
      "automatable": false
    },
    {
      "index": 207,
      "name": "Contr. 114",
      "min": 0,
      "max": 1,
      "default": 0,
      "group": "general",
      "type": "continuous",
      "automatable": false
    },
    {
      "index": 208,
      "name": "Contr. 115",
      "min": 0,
      "max": 1,
      "default": 0,
      "group": "general",
      "type": "continuous",
      "automatable": false
    },
    {
      "index": 209,
      "name": "Contr. 116",
      "min": 0,
      "max": 1,
      "default": 0,
      "group": "general",
      "type": "continuous",
      "automatable": false
    },
    {
      "index": 210,
      "name": "Contr. 117",
      "min": 0,
      "max": 1,
      "default": 0,
      "group": "general",
      "type": "continuous",
      "automatable": false
    },
    {
      "index": 211,
      "name": "Contr. 118",
      "min": 0,
      "max": 1,
      "default": 0,
      "group": "general",
      "type": "continuous",
      "automatable": false
    },
    {
      "index": 212,
      "name": "Contr. 119",
      "min": 0,
      "max": 1,
      "default": 0,
      "group": "general",
      "type": "continuous",
      "automatable": false
    },
    {
      "index": 213,
      "name": "Contr. 120",
      "min": 0,
      "max": 1,
      "default": 0,
      "group": "general",
      "type": "continuous",
      "automatable": false
    },
    {
      "index": 214,
      "name": "Reset Ctrl",
      "min": 0,
      "max": 1,
      "default": 0,
      "group": "general",
      "type": "continuous",
      "automatable": false
    },
    {
      "index": 215,
      "name": "Local Ctrl",
      "min": 0,
      "max": 1,
      "default": 0,
      "group": "general",
      "type": "continuous",
      "automatable": false
    },
    {
      "index": 216,
      "name": "AllNoteOff",
      "min": 0,
      "max": 1,
      "default": 0,
      "group": "general",
      "type": "continuous",
      "automatable": false
    },
    {
      "index": 217,
      "name": "OmniModOff",
      "min": 0,
      "max": 1,
      "default": 0,
      "group": "general",
      "type": "continuous",
      "automatable": false
    },
    {
      "index": 218,
      "name": "OmniModeOn",
      "min": 0,
      "max": 1,
      "default": 0,
      "group": "general",
      "type": "continuous",
      "automatable": false
    },
    {
      "index": 219,
      "name": "MonoModeOn",
      "min": 0,
      "max": 1,
      "default": 0,
      "group": "general",
      "type": "continuous",
      "automatable": false
    },
    {
      "index": 220,
      "name": "PolyModeOn",
      "min": 0,
      "max": 1,
      "default": 0,
      "group": "general",
      "type": "continuous",
      "automatable": false
    },
    {
      "index": 221,
      "name": "Channel Aftertouch",
      "min": 0,
      "max": 1,
      "default": 0,
      "group": "general",
      "type": "continuous",
      "automatable": false
    },
    {
      "index": 222,
      "name": "Pitch Bend",
      "min": 0,
      "max": 1,
      "default": 0.5,
      "group": "general",
      "type": "continuous",
      "automatable": false
    }
  ],
  "groups": {
    "general": {
      "name": "general",
      "parameters": [
        0,
        1,
        2,
        3,
        4,
        5,
        6,
        15,
        16,
        25,
        26,
        29,
        30,
        35,
        36,
        37,
        38,
        41,
        42,
        44,
        46,
        47,
        48,
        49,
        50,
        51,
        52,
        53,
        54,
        55,
        57,
        58,
        59,
        60,
        61,
        62,
        63,
        64,
        65,
        66,
        67,
        72,
        73,
        74,
        78,
        79,
        80,
        81,
        82,
        83,
        84,
        85,
        86,
        90,
        91,
        92,
        93,
        94,
        95,
        96,
        97,
        98,
        99,
        101,
        102,
        104,
        105,
        106,
        107,
        108,
        109,
        110,
        111,
        112,
        113,
        114,
        115,
        116,
        117,
        118,
        119,
        120,
        121,
        122,
        123,
        124,
        125,
        126,
        127,
        128,
        129,
        130,
        131,
        132,
        133,
        134,
        136,
        137,
        138,
        139,
        140,
        141,
        142,
        143,
        144,
        145,
        146,
        147,
        148,
        149,
        150,
        151,
        152,
        153,
        154,
        155,
        156,
        157,
        158,
        159,
        160,
        161,
        162,
        163,
        164,
        165,
        166,
        167,
        168,
        169,
        170,
        171,
        172,
        173,
        174,
        175,
        176,
        177,
        178,
        179,
        180,
        181,
        182,
        183,
        184,
        185,
        186,
        187,
        188,
        189,
        190,
        191,
        192,
        193,
        194,
        195,
        196,
        197,
        198,
        199,
        200,
        201,
        202,
        203,
        204,
        205,
        206,
        207,
        208,
        209,
        210,
        211,
        212,
        213,
        214,
        215,
        216,
        217,
        218,
        219,
        220,
        221,
        222
      ]
    },
    "oscillator": {
      "name": "oscillator",
      "parameters": [
        7,
        8,
        9,
        10,
        11,
        12
      ]
    },
    "filter": {
      "name": "filter",
      "parameters": [
        13,
        14,
        27,
        28
      ]
    },
    "envelope": {
      "name": "envelope",
      "parameters": [
        17,
        18,
        19,
        20,
        21,
        22,
        23,
        24,
        31,
        32,
        33,
        34,
        39,
        40
      ]
    },
    "mixer": {
      "name": "mixer",
      "parameters": [
        43,
        68,
        69,
        70,
        71,
        100
      ]
    },
    "effects": {
      "name": "effects",
      "parameters": [
        45,
        56,
        87
      ]
    },
    "panning": {
      "name": "panning",
      "parameters": [
        75,
        76,
        77,
        103,
        135
      ]
    },
    "lfo": {
      "name": "lfo",
      "parameters": [
        88,
        89
      ]
    }
  }
}